README.md
setup.py
src/vdk/plugin/ipython/__init__.py
src/vdk/plugin/ipython/common.py
src/vdk/plugin/ipython/ingest.py
src/vdk/plugin/ipython/job.py
src/vdk/plugin/ipython/sql.py
src/vdk_ipython.egg-info/PKG-INFO
src/vdk_ipython.egg-info/SOURCES.txt
src/vdk_ipython.egg-info/dependency_links.txt
src/vdk_ipython.egg-info/entry_points.txt
src/vdk_ipython.egg-info/requires.txt
src/vdk_ipython.egg-info/top_level.txt
tests/test_ingest.py
tests/test_job_control.py
tests/test_sql.py