Metadata-Version: 2.1
Name: vdk-ipython
Version: 0.2.1184833162
Summary: Ipython extension for VDK
Home-page: https://github.com/vmware/versatile-data-kit
Classifier: Development Status :: 2 - Pre-Alpha
Classifier: License :: OSI Approved :: Apache Software License
Classifier: Programming Language :: Python :: 3.7
Classifier: Programming Language :: Python :: 3.8
Classifier: Programming Language :: Python :: 3.9
Classifier: Programming Language :: Python :: 3.10
Classifier: Programming Language :: Python :: 3.11
Classifier: Framework :: IPython
Requires-Dist: vdk-core
Requires-Dist: iPython
Requires-Dist: pandas
Provides-Extra: data-sources
Requires-Dist: vdk-data-sources; extra == "data-sources"
